aioptdevices/__init__.py
aioptdevices/__main__.py
aioptdevices/configuration.py
aioptdevices/errors.py
aioptdevices/interface.py
aioptdevices/py.typed
aioptdevices-2025.12.4.dist-info/licenses/LICENSE
aioptdevices-2025.12.4.dist-info/METADATA
aioptdevices-2025.12.4.dist-info/WHEEL
aioptdevices-2025.12.4.dist-info/entry_points.txt
aioptdevices-2025.12.4.dist-info/top_level.txt
aioptdevices-2025.12.4.dist-info/RECORD
