Metadata-Version: 2.4
Name: aioptdevices
Version: 2025.12.4
Author-email: Matthew Gibson <matthew.gibzon@gmail.com>
Classifier: Programming Language :: Python :: 3
Classifier: License :: OSI Approved :: GNU General Public License v3 (GPLv3)
Requires-Python: >=3.12
License-File: LICENSE
Requires-Dist: aiohttp>3.9
Requires-Dist: orjson>3.9
Provides-Extra: requirements
Requires-Dist: aiohttp>3.9; extra == "requirements"
Requires-Dist: orjson>3.9; extra == "requirements"
Requires-Dist: pytest; extra == "requirements"
Provides-Extra: requirements-test
Requires-Dist: aioresponses==0.7.6; extra == "requirements-test"
Requires-Dist: mypy==1.10.1; extra == "requirements-test"
Requires-Dist: pytest==8.2.2; extra == "requirements-test"
Requires-Dist: pytest-aiohttp==1.0.5; extra == "requirements-test"
Requires-Dist: pytest-asyncio==0.23.7; extra == "requirements-test"
Requires-Dist: pytest-cov==5.0.0; extra == "requirements-test"
Requires-Dist: ruff==0.5.1; extra == "requirements-test"
Requires-Dist: trustme==1.1.0; extra == "requirements-test"
Requires-Dist: types-orjson==3.6.2; extra == "requirements-test"
Dynamic: license-file
